once/__init__.py
once/_iterator_wrappers.py
once/py.typed
once_py-0.0.7.dist-info/METADATA
once_py-0.0.7.dist-info/WHEEL
once_py-0.0.7.dist-info/licenses/LICENSE
once_py-0.0.7.dist-info/RECORD
