Metadata-Version: 2.4
Name: once-py
Version: 0.0.7
Summary: Utility for initialization ensuring functions are called only once
Project-URL: source_archive, https://github.com/DelfinaCare/once/archive/782c52420d1e0c6792d153cb75ac482b0319e341.zip
Author-email: "Ali.Ebrahim" <ali@delfina.com>
License-Expression: MIT
License-File: LICENSE
Classifier: License :: OSI Approved :: MIT License
Classifier: Operating System :: OS Independent
Classifier: Programming Language :: Python :: 3
Requires-Python: >=3.10
